[
  {
    "type":   "gear",
    "rarity": "header-gs",
    "vendor": "DZ 09",
    "score":  "256",
    "name":   "Lone Star Mask",
    "armor":  "894",
    "price":  "DZ 249,696",
    "fire":   "1240",
    "stam":   "-",
    "elec":   "-",
    "major":  "7% Enemy Armor Damage",
    "minor":  "9% Damage to Elites"
  },
  {
    "type":   "gear",
    "rarity": "header-gs",
    "vendor": "DZ 09",
    "score":  "256",
    "name":   "DeadEYE Chest",
    "armor":  "1,832",
    "price":  "DZ 277,440",
    "fire":   "-",
    "stam":   "1194",
    "elec":   "-",
    "major":  "4% All Resistance<br/>9.5% Exotic Damage Resilience",
    "minor":  "26% Increased Kill XP"
  },
  {
    "type":   "gear",
    "rarity": "header-gs",
    "vendor": "DZ 09",
    "score":  "256",
    "name":   "Tactician's Authority Backpack",
    "armor":  "1,319",
    "price":  "DZ 277,440",
    "fire":   "-",
    "stam":   "-",
    "elec":   "1169",
    "major":  "7% Critical Hit Damage",
    "minor":  "17% Burn Resistance"
  },
  {
    "type":   "gear",
    "rarity": "header-gs",
    "vendor": "DZ 09",
    "score":  "256",
    "name":   "FireCrest Pads",
    "armor":  "1,545",
    "price":  "DZ 221,952",
    "fire":   "-",
    "stam":   "1147",
    "elec":   "-",
    "major":  "3% All Resistance",
    "minor":  "29% Disrupt Resistance<br/>30% Blind/Deaf Resistance<br/>28% Bleed Resistance"
  },
  {
    "type":   "gear",
    "rarity": "header-gs",
    "vendor": "DZ 09",
    "score":  "256",
    "name":   "Tactician's Authority Holster",
    "armor":  "862",
    "price":  "DZ 194,208",
    "fire":   "1125",
    "stam":   "1256",
    "elec":   "1149",
    "major":  "3.5% Critical Hit Chance",
    "minor":  "-"
  },
  {
    "type":   "gear",
    "rarity": "header-gs",
    "vendor": "DZ 09",
    "score":  "256",
    "name":   "Sentry's Call Gloves",
    "armor":  "892",
    "price":  "DZ 221,952",
    "fire":   "1175",
    "stam":   "-",
    "elec":   "-",
    "major":  "2,366 Pistol Damage<br/>1,236 LMG Damage<br/>14% Critical Hit Damage",
    "minor":  "-"
  },
  {
    "type":       "weapon-mod",
    "vendor":     "DZ 09",
    "name":       "Quick release magazine",
    "price":      "DZ 21,362",
    "attributes": "27% Reload Speed<br/>11% Magazine Size<br/>4.8% Rate of Fire"
  },
  {
    "type":       "weapon-mod",
    "vendor":     "DZ 09",
    "name":       "SR-7 Suppressor",
    "price":      "DZ 24,137",
    "attributes": "19% Critical Hit Damage<br/>4.5% Optimal Range<br/>2.5% Stability<br/>45% Reduced Threat"
  },
  {
    "type":       "weapon-mod",
    "vendor":     "DZ 09",
    "name":       "Vertical Grip",
    "price":      "DZ 24,137",
    "attributes": "47% Optimal Range<br/>2.5% Stability<br/>4% Critical Hit Damage"
  },
  {
    "type":       "weapon-mod",
    "vendor":     "DZ 09",
    "name":       "EXPS3 Holographic sight",
    "price":      "DZ 24,137",
    "attributes": "24% Optimal Range<br/>3% Critical Hit Chance<br/>2% Accuracy"
  },
  {
    "type":   "gear",
    "rarity": "header-gs",
    "vendor": "DZ 08",
    "score":  "256",
    "name":   "Reclaimer Mask",
    "armor":  "930",
    "price":  "DZ 249,696",
    "fire":   "1197",
    "stam":   "-",
    "elec":   "-",
    "major":  "7% Enemy Armor Damage",
    "minor":  "9% Damage to Elites"
  },
  {
    "type":   "gear",
    "rarity": "header-gs",
    "vendor": "DZ 08",
    "score":  "256",
    "name":   "AlphaBridge Chest",
    "armor":  "1,767",
    "price":  "DZ 277,440",
    "fire":   "-",
    "stam":   "1131",
    "elec":   "-",
    "major":  "4% Health on Kill<br/>5% Enemy Armor Damage",
    "minor":  "27% Increased Kill XP"
  },
  {
    "type":   "gear",
    "rarity": "header-gs",
    "vendor": "DZ 08",
    "score":  "256",
    "name":   "Reclaimer Backpack",
    "armor":  "1,221",
    "price":  "DZ 277,440",
    "fire":   "-",
    "stam":   "-",
    "elec":   "1142",
    "major":  "13,124 Skill Power",
    "minor":  "15% Disrupt Resistance"
  },
  {
    "type":   "gear",
    "rarity": "header-gs",
    "vendor": "DZ 08",
    "score":  "256",
    "name":   "Hunter's Faith Knee Pads",
    "armor":  "1,613",
    "price":  "DZ 221,952",
    "fire":   "-",
    "stam":   "1121",
    "elec":   "-",
    "major":  "14,555 Health",
    "minor":  "31% Shock Resistance<br/>33% Blind/Deaf Resistance<br/>33% Burn Resistance"
  },
  {
    "type":   "gear",
    "rarity": "header-gs",
    "vendor": "DZ 08",
    "score":  "256",
    "name":   "Reclaimer Holster",
    "armor":  "868",
    "price":  "DZ 194,208",
    "fire":   "1187",
    "stam":   "1165",
    "elec":   "1133",
    "major":  "7,545 Health",
    "minor":  "-"
  },
  {
    "type":   "gear",
    "rarity": "header-gs",
    "vendor": "DZ 08",
    "score":  "256",
    "name":   "Sentry's Call Gloves",
    "armor":  "992",
    "price":  "DZ 221,952",
    "fire":   "1243",
    "stam":   "-",
    "elec":   "-",
    "major":  "1,303 LMG Damage<br/>14% Critical Hit Damage<br/>7% Enemy Armor Damage",
    "minor":  "-"
  },
  {
    "type":   "gear",
    "rarity": "header-he",
    "vendor": "DZ 08",
    "score":  "256",
    "name":   "Tenacious Mask",
    "armor":  "912",
    "price":  "DZ 249,696",
    "fire":   "-",
    "stam":   "1125",
    "elec":   "-",
    "major":  "8,664 Skill Power",
    "minor":  "15% Blind/Deaf Resistance"
  },
  {
    "type":   "gear",
    "rarity": "header-he",
    "vendor": "DZ 08",
    "score":  "256",
    "name":   "Robust Chest",
    "armor":  "1,790",
    "price":  "DZ 277,440",
    "fire":   "-",
    "stam":   "1253",
    "elec":   "-",
    "major":  "4% Health on Kill<br/>5% Enemy Armor Damage",
    "minor":  "27% Increased Kill XP"
  },
  {
    "type":   "gear",
    "rarity": "header-he",
    "vendor": "DZ 08",
    "score":  "256",
    "name":   "Technical Backpack",
    "armor":  "1,235",
    "price":  "DZ 277,440",
    "fire":   "-",
    "stam":   "1193",
    "elec":   "-",
    "major":  "11,430 Health",
    "minor":  "52% Ammo Capacity"
  },
  {
    "type":   "gear",
    "rarity": "header-he",
    "vendor": "DZ 08",
    "score":  "256",
    "name":   "Prosperous Knee Pads",
    "armor":  "1,531",
    "price":  "DZ 221,952",
    "fire":   "-",
    "stam":   "1163",
    "elec":   "-",
    "major":  "16,477 Health",
    "minor":  "46% Increased Kill XP<br/>32% Burn Resistance<br/>32% Blind/Deaf Resistance"
  },
  {
    "type":   "gear",
    "rarity": "header-he",
    "vendor": "DZ 08",
    "score":  "256",
    "name":   "Steadfast Holster",
    "armor":  "906",
    "price":  "DZ 194,208",
    "fire":   "1114",
    "stam":   "1226",
    "elec":   "1115",
    "major":  "4% Critical Hit Chance",
    "minor":  "-"
  },
  {
    "type":   "gear",
    "rarity": "header-he",
    "vendor": "DZ 08",
    "score":  "256",
    "armor":  "992",
    "name":   "Decisive Gloves",
    "price":  "DZ 221,952",
    "fire":   "-",
    "stam":   "1153",
    "elec":   "-",
    "major":  "7.5% Enemy Armor Damage<br/>4,203 Marksman Rifle Damage<br/>5% Critical Hit Chance",
    "minor":  "-"
  },
  {
    "type":       "gear-mod",
    "name":       "Stamina Mod",
    "vendor":     "East 64th St",
    "stat":       "241 STA",
    "price":      "DZ 21,362",
    "attribute":  "2,886 Skill Power"
  },
  {
    "type":       "gear-mod",
    "name":       "Performance Mod",
    "vendor":     "East 64th St",
    "stat":       "-",
    "price":      "DZ 21,362",
    "attribute":  "6% First Aid Ally Heal"
  },
  {
    "type":       "weapon-mod",
    "vendor":     "East 61st St",
    "name":       "Extended magazine",
    "price":      "DZ 21,362",
    "attributes": "110% Magazine Size<br/>4.5% Reload Speed<br/>3% Critical Hit Chance"
  },
  {
    "type":       "weapon-mod",
    "vendor":     "East 61st St",
    "name":       "Omega rifle suppressor - Tan",
    "price":      "DZ 24,137",
    "attributes": "17.5% Headshot Damage<br/>2% Accuracy<br/>3% Critical Hit Chance<br/>41% Reduced Threat"
  },
  {
    "type":       "weapon-mod",
    "vendor":     "East 61st St",
    "name":       "Handstop - Coyote",
    "price":      "DZ 24,137",
    "attributes": "29.5% Reload Speed<br/>2.5% Stability<br/>2% Accuracy"
  },
  {
    "type":       "weapon-mod",
    "vendor":     "East 61st St",
    "name":       "Small RDS Scope",
    "price":      "DZ 24,137",
    "attributes": "13% Stability<br/>3% Critical Hit Chance<br/>2% Accuracy"
  },
  {
    "type":   "gear",
    "rarity": "header-he",
    "vendor": "East 58th St",
    "score":  "256",
    "name":   "Enduring Mask",
    "armor":  "882",
    "price":  "DZ 249,696",
    "fire":   "1196",
    "stam":   "-",
    "elec":   "-",
    "major":  "4% All Resistance",
    "minor":  "14% Increased Kill XP"
  },
  {
    "type":   "gear",
    "rarity": "header-he",
    "vendor": "East 58th St",
    "score":  "256",
    "name":   "Reckless Chest",
    "armor":  "1,901",
    "price":  "DZ 277,440",
    "fire":   "1199",
    "stam":   "-",
    "elec":   "-",
    "major":  "4% All Resistance<br/>8% Skill Haste",
    "minor":  "28% Increased Kill XP"
  },
  {
    "type":   "gear",
    "rarity": "header-he",
    "vendor": "East 58th St",
    "score":  "256",
    "name":   "Inventive Backpack",
    "armor":  "1,180",
    "price":  "DZ 277,440",
    "fire":   "-",
    "stam":   "1121",
    "elec":   "-",
    "major":  "7% Critical Hit Damage",
    "minor":  "15% Bleed Resistance"
  },
  {
    "type":   "gear",
    "rarity": "header-he",
    "vendor": "East 58th St",
    "score":  "256",
    "name":   "Accomplished Knee Pads",
    "armor":  "1,469",
    "price":  "DZ 221,952",
    "fire":   "-",
    "stam":   "-",
    "elec":   "1235",
    "major":  "7% Critical Hit Damage",
    "minor":  "13% Damage to Elites<br/>30% Shock Resistance<br/>47% Increased Kill XP"
  },
  {
    "type":   "gear",
    "rarity": "header-he",
    "vendor": "East 58th St",
    "score":  "256",
    "name":   "Steadfast Holster",
    "armor":  "893",
    "price":  "DZ 194,208",
    "fire":   "1147",
    "stam":   "1115",
    "elec":   "1272",
    "major":  "7,945 Health",
    "minor":  "-"
  },
  {
    "type":   "gear",
    "rarity": "header-he",
    "vendor": "East 58th St",
    "score":  "256",
    "name":   "Decisive Gloves",
    "armor":  "869",
    "price":  "DZ 221,952",
    "fire":   "-",
    "stam":   "-",
    "elec":   "1169",
    "major":  "16% Critical Hit Damage<br/>7.5% Enemy Armor Damage<br/>5% Critical Hit Chance",
    "minor":  "-"
  },
  {
    "type":     "weapon",
    "vendor":   "Park Ave",
    "score":    "256",
    "price":    "DZ 332,928",
    "name":     "Police 686 Magnum",
    "bonus":    "-",
    "dmg":      "29.5K",
    "rpm":      "350",
    "mag":      "6",
    "talent1":  "Expert",
    "talent2":  "Adept",
    "talent3":  "-"
  },
  {
    "type":     "weapon",
    "vendor":   "Park Ave",
    "score":    "256",
    "price":    "DZ 416,160",
    "name":     "Black Market T821",
    "bonus":    "19.5% Critical Hit Chance",
    "dmg":      "16.8K",
    "rpm":      "550",
    "mag":      "32",
    "talent1":  "Determined",
    "talent2":  "Capable",
    "talent3":  "Accurate"
  },
  {
    "type":     "weapon",
    "vendor":   "Park Ave",
    "score":    "256",
    "price":    "DZ 416,160",
    "name":     "Black Market AK-74",
    "bonus":    "19% Enemy Armor Damage",
    "dmg":      "20.3K",
    "rpm":      "600",
    "mag":      "30",
    "talent1":  "Responsive",
    "talent2":  "Determined",
    "talent3":  "Competent"
  },
  {
    "type":     "weapon",
    "vendor":   "Park Ave",
    "score":    "256",
    "price":    "DZ 416,160",
    "name":     "Marine Super 90",
    "bonus":    "336.5% Stagger",
    "dmg":      "96.8K",
    "rpm":      "150",
    "mag":      "8",
    "talent1":  "Talented",
    "talent2":  "Responsive",
    "talent3":  "Determined"
  },
  {
    "type":     "weapon",
    "vendor":   "Park Ave",
    "score":    "256",
    "price":    "DZ 416,160",
    "name":     "SRS A1",
    "bonus":    "152% Headshot Damage",
    "dmg":      "96.6K",
    "rpm":      "53",
    "mag":      "7",
    "talent1":  "Trained",
    "talent2":  "Determiend",
    "talent3":  "Balanced"
  },
  {
    "type":     "weapon",
    "vendor":   "Park Ave",
    "score":    "256",
    "price":    "DZ 416,160",
    "name":     "Military RPK-74 M",
    "bonus":    "13% DMG out of cover",
    "dmg":      "14K",
    "rpm":      "650",
    "mag":      "45",
    "talent1":  "Destructive",
    "talent2":  "Meticulous",
    "talent3":  "Competent"
  }
]
