[
  {
    "type":   "gear",
    "rarity": "header-he",
    "vendor": "DZ West 53rd",
    "score":  "256",
    "name":   "Decisive Gloves",
    "armor":  "965",
    "price":  "DZ 221,952",
    "fire":   "1129",
    "stam":   "-",
    "elec":   "-",
    "major":  "2,643 Pistol Damage<br/>4,470 MMR Damage<br/>14% CHD",
    "minor":  "-"
  },
  {
    "type":       "gear-mod",
    "vendor":     "DZ West 53rd",
    "name":       "Electronics Mod",
    "stat":       "245 ELE",
    "price":      "DZ 21,362",
    "attribute":  "2,963 Health"
  },
  {
    "type":       "weapon-mod",
    "vendor":     "DZ West 53rd",
    "name":       "Osprey .45 Suppressor - FDE",
    "price":      "DZ 24,137",
    "attributes": "15% Accuracy<br/>5% optimal Range<br/>4% CHD<br/>45% Reduced Threat"
  },
  {
    "type":   "gear",
    "rarity": "header-he",
    "vendor": "DZ West 46th",
    "score":  "256",
    "name":   "Sturdy Holster",
    "armor":  "856",
    "price":  "DZ 194,208",
    "fire":   "1196",
    "stam":   "1135",
    "elec":   "1195",
    "major":  "6% Skill Haste",
    "minor":  "-"
  },
  {
    "type":       "gear-mod",
    "vendor":     "DZ West 46th",
    "name":       "Performance Mod",
    "stat":       "-",
    "price":      "DZ 21,362",
    "attribute":  "3.5% Seeker Mine Damage"
  },
  {
    "type":       "weapon-mod",
    "vendor":     "DZ West 46th",
    "name":       "Omega Rifle Suppressor",
    "price":      "DZ 24,137",
    "attributes": "16.5% Headshot Damage<br/>2.5% Stability<br/>4.5% Optimal Range"
  },
  {
    "type":   "gear",
    "rarity": "header-he",
    "vendor": "DZ West 42nd",
    "score":  "256",
    "name":   "Rapid Chest",
    "price":  "DZ 277,440",
    "armor":  "1,733",
    "fire":   "-",
    "stam":   "-",
    "elec":   "1191",
    "major":  "5% HoK<br/>7% Skill Haste",
    "minor":  "49% Ammo Capacity"
  },
  {
    "type":       "gear-mod",
    "vendor":     "DZ West 42nd",
    "name":       "Electronics Mod",
    "price":      "DZ 21,362",
    "stat":       "229 ELE",
    "attribute":  "2.5% EDR"
  },
  {
    "type":       "weapon-mod",
    "vendor":     "DZ West 42nd",
    "name":       "Extended Magazine",
    "price":      "DZ 21,362",
    "attributes": "118% Mag Size<br/>4.5% Reload Speed<br/>4% CHD"
  },
  {
    "type":   "gear",
    "rarity": "header-he",
    "vendor": "DZ West 39th",
    "score":  "256",
    "name":   "Accomplished Kneepads",
    "price":  "DZ 221,952",
    "armor":  "1,519",
    "fire":   "1116",
    "stam":   "-",
    "elec":   "-",
    "major":  "12,484 Skill Power",
    "minor":  "47% Kill XP<br/>13% DtE<br/>31% Blind/Deaf"
  },
  {
    "type":       "gear-mod",
    "vendor":     "DZ West 39th",
    "name":       "Electronics Mod",
    "stat":       "239 ELE",
    "price":      "DZ 21,362",
    "attribute":  "3,149 Health"
  },
  {
    "type":       "weapon-mod",
    "vendor":     "DZ West 39th",
    "name":       "High Velocity Magazine",
    "price":      "DZ 21,362",
    "attributes": "7% CHC<br/>5% Reload Speed<br/>4% CHD"
  },
  {
    "type":   "gear",
    "rarity": "header-he",
    "vendor": "DZ West 34th",
    "score":  "256",
    "name":   "Prosperous Knee Pads",
    "price":  "DZ 221,952",
    "armor":  "1,617",
    "fire":   "-",
    "stam":   "1194",
    "elec":   "-",
    "major":  "15,866 Health",
    "minor":  "54% Kill XP<br/>28% Disrupt<br/>31% Blind/Deaf"
  },
  {
    "type":       "gear-mod",
    "vendor":     "DZ West 34th",
    "name":       "Stamina Mod",
    "price":      "DZ 21,362",
    "stat":       "256 STAM",
    "attribute":  "3,001 Skill Power"
  },
  {
    "type":       "weapon-mod",
    "vendor":     "DZ West 34th",
    "name":       "Osprey .45 Suppressor",
    "price":      "DZ 24,137",
    "attributes": "15.5% Accuracy<br/>6% Headshot Damage<br/>4.5% Optimal Range<br/>47% Reduced Threat"
  },
  {
    "type":   "gear",
    "rarity": "header-he",
    "vendor": "DZ West 31st",
    "score":  "256",
    "name":   "Rehabilitated Mask",
    "price":  "DZ 249,696",
    "armor":  "875",
    "fire":   "1225",
    "stam":   "-",
    "elec":   "-",
    "major":  "7.5% EAD",
    "minor":  "16% Disorient"
  },
  {
    "type":       "gear-mod",
    "vendor":     "DZ West 31st",
    "name":       "Stamina Mod",
    "price":      "DZ 21,362",
    "stat":       "261 STA",
    "attribute":  "3% Skill Haste"
  },
  {
    "type":       "weapon-mod",
    "vendor":     "DZ West 31st",
    "name":       "Quick Release Magazine",
    "price":      "DZ 21,362",
    "attributes": "29.5% Reload Speed<br/>4% CHD<br/>5.1% RoF"
  },
  {
    "type":   "gear",
    "rarity": "header-he",
    "vendor": "DZ 5th Ave",
    "score":  "256",
    "name":   "Reckless Chest",
    "price":  "DZ 277,440",
    "armor":  "1,804",
    "fire":   "-",
    "stam":   "-",
    "elec":   "1242",
    "major":  "15,949 Health<br/>4% All Resistance",
    "minor":  "56% Ammo Capacity"
  },
  {
    "type":       "gear-mod",
    "vendor":     "DZ 5th Ave",
    "name":       "Performance Mod",
    "price":      "DZ 21,362",
    "stat":       "-",
    "attribute":  "3.5% Sticky Bomb Damage"
  },
  {
    "type":       "weapon-mod",
    "vendor":     "DZ 5th Ave",
    "name":       "Flash Hider",
    "price":      "DZ 24,137",
    "attributes": "15% Accuracy<br/>4% CHD<br/>5.5% Headshot Damage"
  }
]
