[
 {
   "type": "weapon-mod",
   "vendor": "DZ East 53rd",
   "name": "Reflex Sight - Tan",
   "price": "DZ 24,137",
   "attributes": "5% Optimal Range<br/>2.50% Stability<br/>2% Accuracy ",
   "recommended": "No"
 },
 {
   "type": "weapon-mod",
   "vendor": "DZ East 46th",
   "name": "Compensator",
   "price": "DZ 24,137",
   "attributes": "11.50% Stability<br/>2% Accuracy<br/>4% Critical Hit Damage ",
   "recommended": "No"
 },
 {
   "type": "weapon-mod",
   "vendor": "DZ East 42nd",
   "name": "Extended Magazine",
   "price": "DZ 21,362",
   "attributes": "110% Magazine Size<br/>4% Critical Hit Damage<br/>4.70% Rate of Fire ",
   "recommended": "No"
 },
 {
   "type": "weapon-mod",
   "vendor": "DZ East 40th",
   "name": "Angled Grip",
   "price": "DZ 24,137",
   "attributes": "13% Stability<br/>4.50% Reload Speed<br/>4.50% Optimal Range ",
   "recommended": "No"
 },
 {
   "type": "weapon-mod",
   "vendor": "DZ East 34th",
   "name": "Russian Red Dot Sight",
   "price": "DZ 24,137",
   "attributes": "15.50% Accuracy<br/>4.50% Optimal Range<br/>4% Critical Hit Damage ",
   "recommended": "No"
 },
 {
   "type": "weapon-mod",
   "vendor": "DZ East 31st",
   "name": "Reflex Sight",
   "price": "DZ 24,137",
   "attributes": "6.50% Critical Hit Chance<br/>2% Accuracy<br/>4.50% Optimal Range ",
   "recommended": "No"
 },
 {
   "type": "weapon-mod",
   "vendor": "DZ West 53rd",
   "name": "Compensator",
   "price": "DZ 24,137",
   "attributes": "13% Stability<br/>5.50% Headshot Damage<br/>2% Accuracy ",
   "recommended": "No"
 },
 {
   "type": "weapon-mod",
   "vendor": "DZ West 46th",
   "name": "ACOG Scope (4x) - Bronze",
   "price": "DZ 24,137",
   "attributes": "16.50% Accuracy<br/>5% Optimal Range<br/>5.50% Headshot Damage ",
   "recommended": "No"
 },
 {
   "type": "weapon-mod",
   "vendor": "DZ West 42nd",
   "name": "Flash Hider",
   "price": "DZ 24,137",
   "attributes": "16% Accuracy<br/>4.50% Optimal Range<br/>2.50% Stability ",
   "recommended": "No"
 },
 {
   "type": "weapon-mod",
   "vendor": "DZ West 39th",
   "name": "Extended Magazine",
   "price": "DZ 21,362",
   "attributes": "116% Magazine Size<br/>2.50% Critical Hit Chance<br/>4.50% Reload Speed ",
   "recommended": "No"
 },
 {
   "type": "weapon-mod",
   "vendor": "DZ West 34th",
   "name": "Muzzle Brake",
   "price": "DZ 24,137",
   "attributes": "12% Stability<br/>6% Headshot Damage<br/>2% Accuracy ",
   "recommended": "No"
 },
 {
   "type": "weapon-mod",
   "vendor": "DZ West 31st",
   "name": "Handstop - OD Green",
   "price": "DZ 24,137",
   "attributes": "29% Reload Speed<br/>4.50% Optimal Range<br/>4% Critical Hit Damage ",
   "recommended": "No"
 },
 {
   "type": "weapon-mod",
   "vendor": "DZ 5th Ave",
   "name": "Small Laser Pointer",
   "price": "DZ 24,137",
   "attributes": "14.50% Accuracy<br/>4.50% Optimal Range<br/>2.50% Stability ",
   "recommended": "No"
 },
 {
   "type": "weapon-mod",
   "vendor": "DZ 05",
   "name": "Extended Magazine",
   "price": "DZ 21,362",
   "attributes": "115% Magazine Size<br/>2.5% Critical Hit Chance<br/>4.6% Rate of Fire ",
   "recommended": "No"
 },
 {
   "type": "weapon-mod",
   "vendor": "DZ 05",
   "name": "Ti-RANT Suppressor",
   "price": "DZ 24,137",
   "attributes": "7.5% Critical Hit Chance<br/>2.5% Stability<br/>2% Accuracy<br/>50% Reduced Threat",
   "recommended": "No"
 },
 {
   "type": "weapon-mod",
   "vendor": "DZ 05",
   "name": "Vertical Grip - Wolf Grey",
   "price": "DZ 24,137",
   "attributes": "45% Optimal Range<br/>5% Reload Speed<br/>2.5% Stability ",
   "recommended": "No"
 },
 {
   "type": "weapon-mod",
   "vendor": "DZ 05",
   "name": "MK5 Scope (15X) - Tan",
   "price": "DZ 24,137",
   "attributes": "6% Headshot Damage<br/>3% Critical Hit Chance<br/>4% Critical Hit Damage ",
   "recommended": "No"
 },
 {
   "type": "weapon-mod",
   "vendor": "DZ 09",
   "name": "Heavy Magazine Spring",
   "price": "DZ 21,362",
   "attributes": "3% Critical Hit Chance<br/>11.5% Magazine Size<br/>10.2% Rate of Fire ",
   "recommended": "No"
 },
 {
   "type": "weapon-mod",
   "vendor": "DZ 09",
   "name": "Compensator",
   "price": "DZ 24,137",
   "attributes": "12% Stability<br/>6% Headshot Damage<br/>2.5% Critical Hit Chance ",
   "recommended": "Yes"
 },
 {
   "type": "weapon-mod",
   "vendor": "DZ 09",
   "name": "Handstop - Foliage Green",
   "price": "DZ 24,137",
   "attributes": "27.5% Reload Speed<br/>4.5% Optimal Range<br/>2% Accuracy ",
   "recommended": "No"
 },
 {
   "type": "weapon-mod",
   "vendor": "DZ 09",
   "name": "ACOG Scope (4x) - FDE",
   "price": "DZ 24,137",
   "attributes": "15% Accuracy<br/>2.5% Stability<br/>6% Headshot Damage ",
   "recommended": "No"
 },
 {
   "type": "weapon-mod",
   "vendor": "East 61st",
   "name": "Heavy Magazine Spring",
   "price": "DZ 21,362",
   "attributes": "4.5% Reload Speed<br/>3% Critical Hit Chance<br/>9.7% Rate of Fire ",
   "recommended": "No"
 },
 {
   "type": "weapon-mod",
   "vendor": "East 61st",
   "name": "Large Suppressor - FDE",
   "price": "DZ 24,137",
   "attributes": "18% Critical Hit Damage<br/>2% Accuracy<br/>2.5% Critical Hit Chance<br/>42% Reduced Threat",
   "recommended": "Yes"
 },
 {
   "type": "weapon-mod",
   "vendor": "East 61st",
   "name": "Vertical Grip - OD Green",
   "price": "DZ 24,137",
   "attributes": "47% Optimal Range<br/>2% Accuracy<br/>4.5% Reload Speed ",
   "recommended": "No"
 },
 {
   "type": "weapon-mod",
   "vendor": "East 61st",
   "name": "CQBSS Scope - FDE",
   "price": "DZ 24,137",
   "attributes": "13% Stability<br/>2% Accuracy<br/>4% Critical Hit Damage ",
   "recommended": "No"
 },
 {
   "type": "weapon-mod",
   "vendor": "The Crypt",
   "name": "Small Grip - Red",
   "price": "$ 174,722",
   "attributes": "17% Critical Hit Damage<br/>2.0% Accuracy<br/>2.50% Stability ",
   "recommended": "No"
 },
 {
   "type": "weapon-mod",
   "vendor": "The Grindhouse",
   "name": "High Velocity Magazine",
   "price": "$ 168,044",
   "attributes": "7.50% Critical Hit Chance<br/>4% Critical Hit Damage<br/>11.0% Magazine Size ",
   "recommended": "No"
 },
 {
   "type": "weapon-mod",
   "vendor": "The Last Call",
   "name": "Osprey .45 Suppressor",
   "price": "$ 174,722",
   "attributes": "16.50% Accuracy<br/>4.50% Optimal Range<br/>6.0% Headshot Damage<br/>42% Reduced Threat",
   "recommended": "No"
 },
 {
   "type": "weapon-mod",
   "vendor": "Wolves Den",
   "name": "Quick Release Magazine",
   "price": "$ 168,044",
   "attributes": "30% Reload Speed<br/>11.5% Magazine Size<br/>2.5% Critical Hit Chance ",
   "recommended": "No"
 },
 {
   "type": "weapon-mod",
   "vendor": "Kerman Station",
   "name": "Extended Magazine",
   "price": "$ 168,044",
   "attributes": "117.5% Magazine Size<br/>4% Critical Hit Damage<br/>5.60% Rate of Fire ",
   "recommended": "No"
 },
 {
   "type": "weapon-mod",
   "vendor": "The Meat Locker",
   "name": "PEQ-15 Laser - Orange",
   "price": "$ 174,722",
   "attributes": "15.0% Accuracy<br/>5.0% Reload Speed<br/>2.50% Stability ",
   "recommended": "Yes"
 },
 {
   "type": "weapon-mod",
   "vendor": "Camp Hudson Weapon Vendor",
   "name": "Extended Magazine",
   "price": "$ 168,044",
   "attributes": "118.5% Magazine Size<br/>4% Critical Hit Damage<br/>5% Reload Speed ",
   "recommended": "No"
 },
 {
   "type": "weapon-mod",
   "vendor": "BoO Weapons Vendor",
   "name": "Handstop - Foliage Green",
   "price": "$ 174,722",
   "attributes": "27.5% Reload Speed<br/>4.5% Optimal Range<br/>3% Stability ",
   "recommended": "No"
 },
 {
   "type": "weapon-mod",
   "vendor": "DZ Vendor at BoO",
   "name": "Angled Grip",
   "price": "DZ 24,137",
   "attributes": "12% Stability<br/>4.5% Optimal Range<br/>4% Critical Hit Damage ",
   "recommended": "Yes"
 },
 {
   "type": "weapon-mod",
   "vendor": "Advanced Weaponry Vendor",
   "name": "High Velocity Magazine",
   "price": "$ 168,044",
   "attributes": "7.5% Critical Hit Chance<br/>4.5% Reload Speed<br/>4% Critical Hit Damage ",
   "recommended": "No"
 },
 {
   "type": "weapon-mod",
   "vendor": "Advanced Weaponry Vendor",
   "name": "SR-7 Suppressor",
   "price": "$ 174,722",
   "attributes": "18% Critical Hit Damage<br/>5.5% Headshot Damage<br/>2.5% Stability<br/>44% Reduced Threat",
   "recommended": "No"
 },
 {
   "type": "weapon-mod",
   "vendor": "Advanced Weaponry Vendor",
   "name": "Handstop - Coyote",
   "price": "$ 174,722",
   "attributes": "29.5% Reload Speed<br/>2.5% Stability<br/>2.5% Accuracy ",
   "recommended": "No"
 },
 {
   "type": "weapon-mod",
   "vendor": "Advanced Weaponry Vendor",
   "name": "PRO Red Dot Sight",
   "price": "$ 174,722",
   "attributes": "18% Critical Hit Damage<br/>4.5% Optimal Range<br/>2.5% Stability ",
   "recommended": "No"
 },
 {
   "type": "weapon-mod",
   "vendor": "Special Equipment Vendor",
   "name": "High Velocity Magazine",
   "price": "PxC 192",
   "attributes": "6.5% Critical Hit Chance<br/>4.5% Reload Speed<br/>11.5% Magazine Size ",
   "recommended": "No"
 },
 {
   "type": "weapon-mod",
   "vendor": "Special Equipment Vendor",
   "name": "Ti-RANT Suppressor",
   "price": "PxC 200",
   "attributes": "7% Critical Hit Chance<br/>4% Critical Hit Damage<br/>5.5% Headshot Damage ",
   "recommended": "No"
 },
 {
   "type": "weapon-mod",
   "vendor": "Special Equipment Vendor",
   "name": "Handstop - OD Green",
   "price": "PxC 200",
   "attributes": "27.5% Reload Speed<br/>4% Critical Hit Damage<br/>4.5% Optimal Range ",
   "recommended": "No"
 },
 {
   "type": "weapon-mod",
   "vendor": "Special Equipment Vendor",
   "name": "VX-1 scope (12x)",
   "price": "PxC 200",
   "attributes": "18.5% Headshot Damage<br/>4.5% Optimal Range<br/>2.5% Stability ",
   "recommended": "No"
 },
 {
   "type": "weapon-mod",
   "vendor": "Camp Clinton",
   "name": "Heavy Magazine Spring",
   "price": "PxC 192",
   "attributes": "2.50% Critical Hit Chance<br/>4% Critical Hit Damage<br/>9.80% Rate of Fire ",
   "recommended": "No"
 },
 {
   "type": "weapon-mod",
   "vendor": "Camp Clinton",
   "name": "Loud Vent Brake",
   "price": "PxC 200",
   "attributes": "18% Critical Hit Damage<br/>4.50% Optimal Range<br/>6.0% Headshot Damage<br/>49% Increased Threat",
   "recommended": "No"
 },
 {
   "type": "weapon-mod",
   "vendor": "Camp Clinton",
   "name": "Handstop - Wolf Grey",
   "price": "PxC 200",
   "attributes": "30.50% Reload Speed<br/>2.50% Stability<br/>4.50% Optimal Range ",
   "recommended": "No"
 },
 {
   "type": "weapon-mod",
   "vendor": "Camp Clinton",
   "name": "Small RDS scope",
   "price": "PxC 200",
   "attributes": "13.50% Stability<br/>4.50% Optimal Range<br/>2.50% Critical Hit Chance ",
   "recommended": "No"
 }
]